Metadata-Version: 2.1
Name: jejejeje
Version: 0.0.1
Summary: isoweek calculation and so on
Home-page: https://github.com/LEEZIIEUN/jejejeje
Author: leejieun
Author-email: jetask@kopo.ac.kr
License: MIT
Keywords: calendar,isoweek,listsum
